{
    "version": [4, 0, 5],
    "files": {
        "ActRec/actrec/functions/__init__.py": [4, 0, 3],
        "ActRec/actrec/functions/categories.py": [4, 0, 3],
        "ActRec/actrec/functions/globals.py": [4, 0, 3],
        "ActRec/actrec/functions/locals.py": [4, 0, 5],
        "ActRec/actrec/functions/macros.py": [4, 0, 5],
        "ActRec/actrec/functions/shared.py": [4, 0, 5],
        "ActRec/actrec/menus/__init__.py": [4, 0, 5],
        "ActRec/actrec/menus/locals.py": [4, 0, 0],
        "ActRec/actrec/menus/categories.py": [4, 0, 5],
        "ActRec/actrec/operators/__init__.py": [4, 0, 1],
        "ActRec/actrec/operators/categories.py": [4, 0, 5],
        "ActRec/actrec/operators/globals.py": [4, 0, 5],
        "ActRec/actrec/operators/helper.py": [4, 0, 0],
        "ActRec/actrec/operators/locals.py": [4, 0, 5],
        "ActRec/actrec/operators/macros.py": [4, 0, 5],
        "ActRec/actrec/operators/preferences.py": [4, 0, 5],
        "ActRec/actrec/operators/shared.py": [4, 0, 5],
        "ActRec/actrec/panels/__init__.py": [4, 0, 0],
        "ActRec/actrec/panels/main.py": [4, 0, 5],
        "ActRec/actrec/properties/__init__.py": [4, 0, 5],
        "ActRec/actrec/properties/categories.py": [4, 0, 0],
        "ActRec/actrec/properties/globals.py": [4, 0, 5],
        "ActRec/actrec/properties/locals.py": [4, 0, 5],
        "ActRec/actrec/properties/macros.py": [4, 0, 5],
        "ActRec/actrec/properties/shared.py": [4, 0, 5],
        "ActRec/actrec/ui_functions/__init__.py": [4, 0, 5],
        "ActRec/actrec/ui_functions/categories.py": [4, 0, 5],
        "ActRec/actrec/ui_functions/globals.py": [4, 0, 5],
        "ActRec/actrec/uilist/__init__.py": [4, 0, 0],
        "ActRec/actrec/uilist/locals.py": [4, 0, 3],
        "ActRec/actrec/uilist/macros.py": [4, 0, 0],
        "ActRec/actrec/__init__.py": [4, 0, 5],
        "ActRec/actrec/config.py": [4, 0, 5],
        "ActRec/actrec/icon_manager.py": [4, 0, 3],
        "ActRec/actrec/keymap.py": [4, 0, 5],
        "ActRec/actrec/log.py": [4, 0, 5],
        "ActRec/actrec/preferences.py": [4, 0, 5],
        "ActRec/actrec/shared_data.py": [4, 0, 5],
        "ActRec/actrec/update.py": [4, 0, 5],
        "ActRec/__init__.py": [4, 0, 5]
    },
    "remove": []
}